{
  "Version": "v1",
  "MappingFields": [
    {
      "Name": "employeeNumber",
      "Description": "[Mandatory]",
      "Type": "Text",
      "MappingActions": [
        {
          "MapForActions": [
            "Create",
            "Update"
          ],
          "MappingMode": "Field",
          "Value": "\"Person.ExternalId\"",
          "UsedInNotifications": false,
          "StoreInAccountData": false
        }
      ]
    },
    {
      "Name": "id",
      "Description": "[Mandatory]",
      "Type": "Text",
      "MappingActions": [
        {
          "MapForActions": [
            "Create",
            "Update"
          ],
          "MappingMode": "None",
          "Value": "\"\"",
          "UsedInNotifications": false,
          "StoreInAccountData": true
        }
      ]
    }
  ],
  "UniqueFieldNames": []
}